yt_dlp_utils/__init__.py
yt_dlp_utils/aio.py
yt_dlp_utils/constants.py
yt_dlp_utils/lib.py
yt_dlp_utils/py.typed
yt_dlp_utils-0.0.7.dist-info/METADATA
yt_dlp_utils-0.0.7.dist-info/WHEEL
yt_dlp_utils-0.0.7.dist-info/licenses/LICENSE.txt
yt_dlp_utils-0.0.7.dist-info/RECORD
