Metadata-Version: 2.4
Name: yt-dlp-utils
Version: 0.0.7
Summary: Utilities for programmatic use of yt-dlp.
License-Expression: MIT
License-File: LICENSE.txt
Keywords: command line,yt-dlp
Author: Andrew Udvare
Author-email: audvare@gmail.com
Requires-Python: >=3.10,<4.0
Classifier: Development Status :: 4 - Beta
Classifier: Intended Audience :: Developers
Classifier: Programming Language :: Python
Classifier: Programming Language :: Python :: 3.10
Classifier: Programming Language :: Python :: 3.11
Classifier: Programming Language :: Python :: 3.12
Classifier: Programming Language :: Python :: 3.13
Classifier: Programming Language :: Python :: 3.14
Classifier: Typing :: Typed
Provides-Extra: asyncio
Requires-Dist: aiohttp (>=3.13.3,<4.0.0) ; extra == "asyncio"
Requires-Dist: aiohttp-retry (>=2.9.1,<3.0.0) ; extra == "asyncio"
Requires-Dist: requests (>=2.32.5,<3.0.0)
Requires-Dist: typing-extensions (>=4.15.0,<5.0.0)
Requires-Dist: yt-dlp[default] (>=2026.1.29,<2027.0.0)
Project-URL: Documentation, https://yt-dlp-utils.readthedocs.org
Project-URL: Homepage, https://tatsh.github.io/yt-dlp-utils/
Project-URL: Issues, https://github.com/Tatsh/yt-dlp-utils/issues
Project-URL: Repository, https://github.com/Tatsh/yt-dlp-utils
